django_pyctx/__init__.py
django_pyctx/admin.py
django_pyctx/apps.py
django_pyctx/helpers.py
django_pyctx/middlewares.py
django_pyctx/models.py
django_pyctx/query_timer.py
django_pyctx/settings.py
django_pyctx/tests.py
django_pyctx/views.py
django_pyctx/migrations/__init__.py
django_pyctx-0.9.0.dist-info/METADATA
django_pyctx-0.9.0.dist-info/WHEEL
django_pyctx-0.9.0.dist-info/licenses/LICENSE
django_pyctx-0.9.0.dist-info/RECORD
