Metadata-Version: 2.4
Name: django-pyctx
Version: 0.9.0
Summary: Context package to use data between function calls, use timers and log it for Django.
Project-URL: Homepage, https://github.com/molcay/django-pyctx
Project-URL: Issues, https://github.com/molcay/django-pyctx/issues
Author-email: "M. Olcay TERCANLI" <molcay@mail.com>
License-Expression: MIT
License-File: LICENSE
Keywords: context,django,django-pyctx,django-req-ctx,pyctx
Classifier: Environment :: Web Environment
Classifier: Framework :: Django
Classifier: Intended Audience :: Developers
Classifier: License :: OSI Approved :: MIT License
Classifier: Operating System :: OS Independent
Classifier: Programming Language :: Python :: 3
Classifier: Programming Language :: Python :: 3.9
Classifier: Programming Language :: Python :: 3.10
Classifier: Programming Language :: Python :: 3.11
Classifier: Programming Language :: Python :: 3.12
Classifier: Programming Language :: Python :: 3.13
Classifier: Programming Language :: Python :: 3.14
Requires-Python: >=3.10
Requires-Dist: django>=5.1
Requires-Dist: pyctx>=0.1.10
